.gitignore
.travis.yml
MANIFEST.in
README.rst
bootstrap.py
buildout.cfg
setup.py
travis.cfg
docs/HISTORY.txt
docs/INSTALL.txt
docs/LICENSE.GPL
docs/LICENSE.txt
src/collective/__init__.py
src/collective.geo.behaviour.egg-info/PKG-INFO
src/collective.geo.behaviour.egg-info/SOURCES.txt
src/collective.geo.behaviour.egg-info/dependency_links.txt
src/collective.geo.behaviour.egg-info/entry_points.txt
src/collective.geo.behaviour.egg-info/namespace_packages.txt
src/collective.geo.behaviour.egg-info/not-zip-safe
src/collective.geo.behaviour.egg-info/requires.txt
src/collective.geo.behaviour.egg-info/top_level.txt
src/collective/geo/__init__.py
src/collective/geo/behaviour/__init__.py
src/collective/geo/behaviour/behaviour.py
src/collective/geo/behaviour/configure.zcml
src/collective/geo/behaviour/interfaces.py
src/collective/geo/behaviour/testing.py
src/collective/geo/behaviour/testing.zcml
src/collective/geo/behaviour/locales/collective.geo.behaviour.pot
src/collective/geo/behaviour/locales/rebuild.sh
src/collective/geo/behaviour/locales/de/LC_MESSAGES/collective.geo.behaviour.po
src/collective/geo/behaviour/locales/es/LC_MESSAGES/collective.geo.behaviour.po
src/collective/geo/behaviour/locales/fr/LC_MESSAGES/collective.geo.behaviour.po
src/collective/geo/behaviour/locales/it/LC_MESSAGES/collective.geo.behaviour.po
src/collective/geo/behaviour/locales/nl/LC_MESSAGES/collective.geo.behaviour.po
src/collective/geo/behaviour/locales/zh_CN/LC_MESSAGES/collective.geo.behaviour.po
src/collective/geo/behaviour/locales/zh_TW/LC_MESSAGES/collective.geo.behaviour.po
src/collective/geo/behaviour/profiles/default/metadata.xml
src/collective/geo/behaviour/profiles/testing/metadata.xml
src/collective/geo/behaviour/profiles/testing/types.xml
src/collective/geo/behaviour/profiles/testing/types/dexterity_content_with_geo_behaviour.xml
src/collective/geo/behaviour/tests/__init__.py
src/collective/geo/behaviour/tests/test_behaviour.py
src/collective/geo/behaviour/tests/test_setup.py