Metadata-Version: 1.1
Name: collective.geo.behaviour
Version: 1.2
Summary: collective.geo Dexterity integration
Home-page: https://github.com/collective/collective.geo.behaviour
Author: UNKNOWN
Author-email: UNKNOWN
License: GPL
Platform: UNKNOWN
Classifier: Framework :: Plone
Classifier: Programming Language :: Python
